narlogs/__init__.py
narlogs-0.1.1.dist-info/METADATA
narlogs-0.1.1.dist-info/WHEEL
narlogs-0.1.1.dist-info/licenses/LICENSE
narlogs-0.1.1.dist-info/RECORD
