Metadata-Version: 2.4
Name: narlogs
Version: 0.1.1
Summary: Utilities to log on dataframe pipelines
Project-URL: repository, https://github.com/koaning/narlogs
Project-URL: issue-tracker, https://github.com/koaning/narlogs/issues
Project-URL: documentation, https://koaning.github.io/narlogs/
Author: Vincent D. Warmerdam
License: MIT License
License-File: LICENSE
Requires-Python: >=3.10
Requires-Dist: humanize
Requires-Dist: narwhals
Requires-Dist: orjson
